solaredge/__init__.py
solaredge/monitoring.py
solaredge-1.1.1.dist-info/WHEEL
solaredge-1.1.1.dist-info/METADATA
solaredge-1.1.1.dist-info/RECORD
