Metadata-Version: 2.3
Name: solaredge
Version: 1.1.1
Summary: Add your description here
Author: evworth
Requires-Dist: httpx>=0.28.1
Requires-Dist: pytz>=2025.2
Requires-Python: >=3.10
